{
  "timestamp": "2026-07-22T06:30:31.233308",
  "host": "192.168.0.43",
  "hostname": "GRUPOEPEM467-VM",
  "disk_e": {
    "size_gb": 246.29,
    "free_gb": 200.68,
    "used_gb": 45.61,
    "used_pct": 18.5,
    "status": "ok"
  },
  "knime": {
    "pid": 12572,
    "mem_gb": 25.6,
    "start_time": "2026-07-21 10:58:12",
    "status": "running"
  },
  "onedrive": {
    "pid": 11896,
    "status": "running"
  },
  "temp_e": {
    "files": 8011,
    "bytes": 37556754766,
    "status": "ok"
  },
  "source": "192.168.0.95"
}