{
  "timestamp": "2026-07-20T08:30:43.411735",
  "host": "192.168.0.43",
  "hostname": "GRUPOEPEM467-VM",
  "disk_e": {
    "size_gb": 246.29,
    "free_gb": 42.95,
    "used_gb": 203.34,
    "used_pct": 82.6,
    "status": "ok"
  },
  "knime": {
    "pid": 2312,
    "mem_gb": 25.52,
    "start_time": "2026-07-14 17:11:33",
    "status": "running"
  },
  "onedrive": {
    "pid": 21532,
    "status": "running"
  },
  "temp_e": {
    "files": 37561,
    "bytes": 193486625146,
    "status": "ok"
  },
  "source": "192.168.0.95"
}